{
    "keyUseCount": {
        "": 4,
        "A": 3,
        "D": 2,
        "Delete": 1,
        "End": 2,
        "Enter": 1,
        "F": 2,
        "I": 2,
        "Insert": 2,
        "K": 1,
        "LeftButton": 2,
        "N": 2,
        "Num *": 2,
        "Num -": 2,
        "Num /": 2,
        "Num 0": 1,
        "Num 1": 3,
        "Num 2": 2,
        "Num 3": 2,
        "Num 4": 3,
        "Num 5": 2,
        "Num 6": 1,
        "Num 7": 1,
        "Num 8": 1,
        "Num 9": 1,
        "Num Lock": 1,
        "Page Down": 3,
        "S": 3,
        "←": 2,
        "→": 2,
        "↓": 2
    },
    "keyUsePerHourCount": {
        "2024.12.21 01:00:00": 104
    },
    "keyUseTotalCount": 104,
    "mouseMoveDistance": 3863.2233971081823
}
